{
  "button11": {
    "logo": "snip.bmp",
    "latch": false,
    "latchlogo": "",
    "actionarray": [
      "5",
      "5",
      "4"
    ],
    "valuearray": [
      "8",
      "2",
      "s"
    ]
  },
  "button12": {
    "logo": "todo.bmp",
    "latch": false,
    "latchlogo": "",
    "actionarray": [
      "5",
      "7",
      "0"
    ],
    "valuearray": [
      "8",
      "2",
      "0"
    ]
  },
  "button13": {
    "logo": "outlook.bmp",
    "latch": false,
    "latchlogo": "",
    "actionarray": [
      "5",
      "7",
      "0"
    ],
    "valuearray": [
      "8",
      "3",
      "0"
    ]
  },
  "button14": {
    "logo": "outlook.bmp",
    "latch": false,
    "latchlogo": "",
    "actionarray": [
      "5",
      "7",
      "0"
    ],
    "valuearray": [
      "8",
      "3",
      "0"
    ]
  },
  "button21": {
    "logo": "explorer.bmp",
    "latch": false,
    "latchlogo": "",
    "actionarray": [
      "5",
      "4",
      "0"
    ],
    "valuearray": [
      "8",
      "e",
      "0"
    ]
  },
  "button22": {
    "logo": "lock.bmp",
    "latch": false,
    "latchlogo": "",
    "actionarray": [
      "5",
      "4",
      "0"
    ],
    "valuearray": [
      "8",
      "l",
      "0"
    ]
  },
  "button23": {
    "logo": "home.bmp",
    "latch": false,
    "latchlogo": "",
    "actionarray": [
      "11",
      "0",
      "0"
    ],
    "valuearray": [
      "6",
      "0",
      "0"
    ]
  },
  "button24": {
    "logo": "home.bmp",
    "latch": false,
    "latchlogo": "",
    "actionarray": [
      "11",
      "0",
      "0"
    ],
    "valuearray": [
      "6",
      "0",
      "0"
    ]
  },
  "button31": {
    "logo": "explorer.bmp",
    "latch": false,
    "latchlogo": "",
    "actionarray": [
      "5",
      "4",
      "0"
    ],
    "valuearray": [
      "8",
      "e",
      "0"
    ]
  },
  "button32": {
    "logo": "lock.bmp",
    "latch": false,
    "latchlogo": "",
    "actionarray": [
      "5",
      "4",
      "0"
    ],
    "valuearray": [
      "8",
      "l",
      "0"
    ]
  },
  "button33": {
    "logo": "home.bmp",
    "latch": false,
    "latchlogo": "",
    "actionarray": [
      "11",
      "0",
      "0"
    ],
    "valuearray": [
      "6",
      "0",
      "0"
    ]
  },
  "button34": {
    "logo": "home.bmp",
    "latch": false,
    "latchlogo": "",
    "actionarray": [
      "11",
      "0",
      "0"
    ],
    "valuearray": [
      "6",
      "0",
      "0"
    ]
  }
}